zendriver/__init__.py
zendriver/_version.py
zendriver/py.typed
zendriver/cdp/README.md
zendriver/cdp/__init__.py
zendriver/cdp/accessibility.py
zendriver/cdp/animation.py
zendriver/cdp/audits.py
zendriver/cdp/autofill.py
zendriver/cdp/background_service.py
zendriver/cdp/bluetooth_emulation.py
zendriver/cdp/browser.py
zendriver/cdp/cache_storage.py
zendriver/cdp/cast.py
zendriver/cdp/console.py
zendriver/cdp/css.py
zendriver/cdp/debugger.py
zendriver/cdp/device_access.py
zendriver/cdp/device_orientation.py
zendriver/cdp/dom.py
zendriver/cdp/dom_debugger.py
zendriver/cdp/dom_snapshot.py
zendriver/cdp/dom_storage.py
zendriver/cdp/emulation.py
zendriver/cdp/event_breakpoints.py
zendriver/cdp/extensions.py
zendriver/cdp/fed_cm.py
zendriver/cdp/fetch.py
zendriver/cdp/file_system.py
zendriver/cdp/headless_experimental.py
zendriver/cdp/heap_profiler.py
zendriver/cdp/indexed_db.py
zendriver/cdp/input_.py
zendriver/cdp/inspector.py
zendriver/cdp/io.py
zendriver/cdp/layer_tree.py
zendriver/cdp/log.py
zendriver/cdp/media.py
zendriver/cdp/memory.py
zendriver/cdp/network.py
zendriver/cdp/overlay.py
zendriver/cdp/page.py
zendriver/cdp/performance.py
zendriver/cdp/performance_timeline.py
zendriver/cdp/preload.py
zendriver/cdp/profiler.py
zendriver/cdp/pwa.py
zendriver/cdp/py.typed
zendriver/cdp/runtime.py
zendriver/cdp/schema.py
zendriver/cdp/security.py
zendriver/cdp/service_worker.py
zendriver/cdp/storage.py
zendriver/cdp/system_info.py
zendriver/cdp/target.py
zendriver/cdp/tethering.py
zendriver/cdp/tracing.py
zendriver/cdp/util.py
zendriver/cdp/web_audio.py
zendriver/cdp/web_authn.py
zendriver/core/_contradict.py
zendriver/core/browser.py
zendriver/core/cloudflare.py
zendriver/core/config.py
zendriver/core/connection.py
zendriver/core/element.py
zendriver/core/expect.py
zendriver/core/intercept.py
zendriver/core/keys.py
zendriver/core/tab.py
zendriver/core/util.py
zendriver-0.15.1.dist-info/METADATA
zendriver-0.15.1.dist-info/WHEEL
zendriver-0.15.1.dist-info/licenses/LICENSE
zendriver-0.15.1.dist-info/RECORD
